cRandom.cpython-37m-darwin.so
cRandom-0.0.4.dist-info/METADATA
cRandom-0.0.4.dist-info/WHEEL
cRandom-0.0.4.dist-info/top_level.txt
cRandom-0.0.4.dist-info/RECORD
