Metadata-Version: 2.1
Name: cRandom
Version: 0.0.4
Summary: Random number generation as in the Book Numerical Recipe.
Home-page: UNKNOWN
Author: Hanjun Goo
Author-email: goohanjun@gmail.com
License: MIT
Platform: UNKNOWN
Classifier: Programming Language :: Python :: 3
Classifier: License :: OSI Approved :: MIT License
Classifier: Operating System :: OS Independent
